{
  "id": "Q0276",
  "text_canonical": "當病情變化大時，我要怎麼保持心情穩定，不被負面情緒影響？",
  "answer": "治療過程中，與醫師保持溝通很重要，對治療進展有疑問時可與醫師討論，幫助您了解每次治療的效果。同時，保持規律的作息很重要，將能幫助您在身心上保持穩定，例如：良好的睡眠、健康飲食和適當的運動，都能讓您的情緒不會劇烈波動。同時，積極尋找讓您快樂的活動，例如與朋友聚會或參與自己喜愛的事情，這些都能幫助您轉移注意力，減少對負面情緒的專注。當壓力或情緒低落時，使用積極的自我對話來鼓勵自己也很重要，可以告訴自己您已經克服了很多治療的挑戰，這能有助於增強您的韌性。您還可以參加癌友支持團體或尋求專業心理諮詢，將能提供情感上的支持，幫助您學習有效應對負面情緒的方法。",
  "source_type": "interview",
  "modality": "verbal",
  "focusp": [
    "O",
    "C"
  ],
  "treatment_phase": [
    "手術後",
    "手術後化放療"
  ],
  "functional_impact": [],
  "心理問題": true,
  "RTW": false,
  "經濟與社會資源": false,
  "危險字詞": false,
  "癌症復發": false,
  "營養照護": false,
  "傷口與症狀照護": false,
  "治療原因與安排": false,
  "口腔復健與身體活動": false,
  "other_condition": null,
  "pii_checked": true,
  "evidence_ref_ids": [
    "REF0111"
  ],
  "version": "2024-11-07"
}