{
  "id": "Q0281",
  "text_canonical": "治療很痛苦，有什麼方法可以讓我不再只專注於痛苦？",
  "answer": "辛苦了！您可以嘗試定期與醫療團隊溝通，討論治療副作用的管理方案，例如使用鎮痛藥或輔助療法，將能幫助您有效地控制症狀。在面對治療帶來的不舒服，分散注意力是個好方法。參與一些讓您放鬆的活動，例如聽音樂、看電視、和家人聊聊天，都能幫助您把注意力轉移到愉快的事情上，讓您不再專注於不舒服的感覺。同時，您還可以使用放鬆技巧，試著練習深呼吸或冥想，放鬆肩膀，閉上眼睛，專心感受每次吸氣和吐氣的節奏，過程中盡量放鬆，這些都能幫助您放鬆身心，減少身體不適的影響。即使在感到不適的時候，保持日常活動也是重要的，哪怕只是輕度運動，如散步或伸展，都能提升您的情緒，並減少對痛苦的關注。",
  "source_type": "interview",
  "modality": "verbal",
  "focusp": [
    "C"
  ],
  "treatment_phase": [
    "手術後",
    "手術後化放療"
  ],
  "functional_impact": [
    "咀嚼困難",
    "吞嚥困難",
    "發音說話困難",
    "張口困難流口水",
    "皮膚紅腫口腔黏膜破損嚴重",
    "口乾嚴重",
    "面部外觀改變",
    "體重減輕營養不良"
  ],
  "心理問題": true,
  "RTW": false,
  "經濟與社會資源": false,
  "危險字詞": false,
  "癌症復發": false,
  "營養照護": false,
  "傷口與症狀照護": false,
  "治療原因與安排": false,
  "口腔復健與身體活動": false,
  "other_condition": null,
  "pii_checked": true,
  "evidence_ref_ids": [
    "REF0113"
  ],
  "version": "2024-11-07"
}